README.md
pyproject.toml
setup.py
simplepygraph/Untitled.ipynb
simplepygraph/__init__.py
simplepygraph/algorithms.py
simplepygraph/constantes.py
simplepygraph/pygraph.py
simplepygraph.egg-info/PKG-INFO
simplepygraph.egg-info/SOURCES.txt
simplepygraph.egg-info/dependency_links.txt
simplepygraph.egg-info/requires.txt
simplepygraph.egg-info/top_level.txt