Metadata-Version: 2.1
Name: simplepygraph
Version: 2.0.5
Summary: Un petit module pour créer des graphes (non orienté, orienté ou bi-partie)
Home-page: https://gitlab.com/sebhoa/pygraph
Author: Sébastien Hoarau
Maintainer: Sébastien Hoarau
License: CC BY-NC-SA 4.0
Keywords: PyGraph package Python graph education vizualisation
Platform: ALL
Classifier: Topic :: Education
Classifier: Topic :: Documentation
Requires-Dist: graphviz
Requires-Dist: networkx
